alef/__init__.py
alef/__main__.py
alef/bash.py
alef/cli.py
alef/logging.py
alef/util.py
alef-0.0.1.dist-info/LICENSE
alef-0.0.1.dist-info/METADATA
alef-0.0.1.dist-info/WHEEL
alef-0.0.1.dist-info/top_level.txt
alef-0.0.1.dist-info/RECORD
