Metadata-Version: 2.1
Name: alef
Version: 0.0.1
Summary: UNKNOWN
Home-page: UNKNOWN
Author: UNKNOWN
Author-email: UNKNOWN
License: UNKNOWN
Platform: UNKNOWN
Requires-Dist: click
Requires-Dist: docker
Requires-Dist: fire
Requires-Dist: redis
